Workbook

Sheet Start_Here
A1: Madison + ~60-Mile Semiconductor / Digital Hardware Search
A3: Generated | B3: 2026-03-30
A4: Goal | B4: Build a 50–60 mile hit list for digital design / RTL / FPGA / embedded-hardware outreach.
A5: Honest read | B5: Strict pure-play semiconductor names near Madison are still limited. The real opportunity set grows when you include FPGA/embedded, instrumentation, quantum, and advanced-energy hardware companies.
A6: Best nearby fit | B6: X-ES is still the clearest local FPGA target; i3, Sound Devices, Sub-Zero, and Johnson broaden the practical search.
A7: Best pure-play fit | B7: SixLine is still the clearest local pure-play semiconductor startup networking target.
A8: Search radius | B8: Add Janesville, Beloit, Reedsburg, Cottage Grove, Middleton, Verona, Sun Prairie, Windsor, and Fitchburg to your search radius.
A9: Suggested first 7 days | D9: What to emphasize in conversation
A10: 1) Read the Companies sheet and sort by Priority Score. | D10: • RTL / SystemVerilog / Verilog coursework and projects
A11: 2) Personalize a 5-sentence outreach note for the top 3 targets. | D11: • FPGA vs MCU vs ASIC understanding
A12: 3) Apply to any visible student / co-op / hardware roles first. | D12: • Timing constraints, synthesis, verification, bring-up
A13: 4) Send cold outreach to founders, recruiting, or engineering leads. | D13: • Interest in low-latency and real hardware systems
A14: 5) Log every message in Tracker_Blank and follow up after 7 days. | D14: • Willingness to start with test / validation / electronics if that gets you in the room
A15: 6) If Madison feels too thin, expand immediately to Middleton, Verona, and Chicago.
A17: Sheets included
A18: Companies | B18: Starter company list with fit scores, links, and next actions
A19: Resources | B19: Places to mine more local leads
A20: Outreach_Template | B20: Cold-email / LinkedIn script you can customize
A21: Tracker_Blank | B21: Use this every time you send a message

Sheet Clubs
A1: UW-Mad Clubs:

Sheet Research
A1: Outreach tracker
A2: Professor | B2: Lab | C2: Research Area | D2: Date Sent | E2: Follow-up due | F2: Response | G2: Next step | H2: Notes
A3: Parmesh Ramanathan | B3: N/A | C3: General | D3: 46174 | F3: No reply yet | G3: wait for reply | H3: asked for general info, not expecting a reply. Ok dope, instant response. Following up is of chief importance, DON’T BE A PUSSY. Schedule the meeting
A4: Daniel Van Der Weide | B4: N/A | C4: General | D4: 5/2/2026, 06/01/2026 | F4: No reply yet | G4: wait for reply | H4: General info, no reply followed up. W, cc follow up from Rob Marshland, should meet up with him for coffee at some point.
A5: Tsung Wei-Huang | B5: n/A | C5: General | D5: 46174 | E5: =IF(D5<>"",D5+7,"") -> 46181 | F5: No reply yet | G5: wait for reply | H5: My literaly advisor, mf better reply on the third email
A6: Julie Hsiao | B6: N/A | C6: General | D6: 46174 | E6: =IF(D6<>"",D6+7,"") -> 46181 | F6: No reply yet | G6: wait for reply | H6: General info, I imagine I'll get a reply.
A7: Georgios Tzimpragoz | B7: N/A | C7: General | D7: 46174 | E7: =IF(D7<>"",D7+7,"") -> 46181 | F7: No reply yet | G7: wait for reply | H7: CompArch guy, idek if he does research. Whatever.
A8: Joshua San Miguel | B8: N/A | C8: General | D8: 46174 | E8: =IF(D8<>"",D8+7,"") -> 46181 | F8: No reply yet | G8: wait for reply | H8: W guy, just lookin for info.
A9: Azadeh Davoodi | B9: N/A | C9: General | D9: 46174 | E9: =IF(D9<>"",D9+7,"") -> 46181 | F9: No reply yet | G9: wait for reply | H9: Undergraduate studies chair, js lookin for info atm
E10: =IF(D10<>"",D10+7,"") | F10: No reply yet
E11: =IF(D11<>"",D11+7,"") | F11: No reply yet
E12: =IF(D12<>"",D12+7,"") | F12: No reply yet
E13: =IF(D13<>"",D13+7,"") | F13: No reply yet
E14: =IF(D14<>"",D14+7,"") | F14: No reply yet
E15: =IF(D15<>"",D15+7,"") | F15: No reply yet
E16: =IF(D16<>"",D16+7,"") | F16: No reply yet
E17: =IF(D17<>"",D17+7,"") | F17: No reply yet
E18: =IF(D18<>"",D18+7,"") | F18: No reply yet

Sheet Companies
A1: Expanded list — semiconductor + digital hardware targets within ~60 miles
A2: Company | B2: City / Area | C2: Segment | D2: Why it belongs on your list | E2: Relevant signal for you | F2: Digital-design fit (1-5) | G2: Student access (1-5) | H2: Priority Score | I2: Website | J2: Careers / Contact | K2: Source 1 | L2: Source 2 | M2: First action | N2: Outreach status | O2: Date contacted | P2: Follow-up due
A3: Extreme Engineering Solutions (X-ES) | B3: Verona | C3: FPGA / embedded computing hardware | D3: Local embedded-computing company with FPGA modules, I/O modules, boards, systems, and on-site manufacturing. | E3: Strongest nearby fit if you want FPGA / board-level digital design; explicit student opportunities. | F3: 5 | G3: 5 | H3: =SUM(F3:G3) -> 10 | I3: https://www.xes-inc.com/ | J3: https://www.xes-inc.com/about/careers/ | K3: https://www.xes-inc.com/about/ | L3: https://www.xes-inc.com/about/careers/student-co-op-opportunities/ | M3: Apply to any student role, then send a short note asking about hardware / FPGA paths. | N3: Not contacted | P3: =IF(O3<>"",O3+7,"")
A4: i3 Product Development | B4: Sun Prairie | C4: Product development / embedded / electrical engineering | D4: Nearby engineering firm with in-house electrical engineering, embedded software, prototyping, and internships. | E4: Great practical fit if you want to talk to real product-development engineers and get hardware exposure fast. | F4: 4 | G4: 5 | H4: =SUM(F4:G4) -> 9 | I4: https://i3pd.com/ | J4: https://i3pd.com/jobs/ | K4: https://i3pd.com/contact-us/ | L4: https://i3pd.com/team/ | M4: Apply to internships or entry paths and mention your interest in embedded / digital hardware projects. | N4: Not contacted | P4: =IF(O4<>"",O4+7,"")
A5: SixLine Semiconductor | B5: Middleton | C5: Pure-play semiconductor startup | D5: Commercializing carbon-nanotube semiconductor technology for next-generation devices. | E5: Best local pure-play semiconductor networking target; founder/startup conversations could be valuable even if openings are sparse. | F5: 4 | G5: 5 | H5: =SUM(F5:G5) -> 9 | I5: https://www.sixlinesemi.com/ | J5: https://www.sixlinesemi.com/contact | K5: https://www.sixlinesemi.com/ | L5: https://wedc.org/innovate-in-wisconsin/innovation-investment-portfolio/sixline-semiconductor-inc/ | M5: Send founder/team outreach asking for a 15-minute learning conversation about local semiconductor paths. | N5: Not contacted | P5: =IF(O5<>"",O5+7,"")
A6: Sound Devices | B6: Madison / Reedsburg | C6: Professional audio / embedded hardware | D6: Designs, assembles, and supports pro-audio and wireless products in Wisconsin; Madison office has embedded roles. | E6: Very solid embedded-hardware target with real products, local engineering, and a history of internships. | F6: 4 | G6: 4 | H6: =SUM(F6:G6) -> 8 | I6: https://www.sounddevices.com/ | J6: https://www.sounddevices.com/company/careers/ | K6: https://www.sounddevices.com/company/careers/ | L6: https://www.sounddevices.com/embedded-software-engineer-madison-wi/ | M6: Reach out to engineering recruiting or apply directly to embedded openings; mention hardware + real-time interest. | N6: Not contacted | P6: =IF(O6<>"",O6+7,"")
A7: Sub-Zero Group | B7: Fitchburg / Madison | C7: Product engineering / controls / appliance electronics | D7: Large local product company with manufacturing and engineering in Fitchburg plus student programs. | E7: Not semiconductor, but a real Wisconsin hardware employer with product-development and controls/electronics paths. | F7: 3 | G7: 5 | H7: =SUM(F7:G7) -> 8 | I7: https://www.subzero-wolf.com/ | J7: https://www.subzero-wolf.com/about/careers | K7: https://www.subzero-wolf.com/about/careers/locations | L7: https://www.subzero-wolf.com/about/careers/co-op-program | M7: Watch student and engineering openings; tailor outreach to product development, controls, or electronics. | N7: Not contacted | P7: =IF(O7<>"",O7+7,"")
A8: Johnson Health Tech | B8: Cottage Grove | C8: Connected products / electronics / embedded systems | D8: Cottage Grove engineering team has posted senior electrical and embedded software roles for connected products. | E8: Good nearby product-electronics company if you want analog/digital hardware, system connectivity, and firmware-adjacent work. | F8: 4 | G8: 3 | H8: =SUM(F8:G8) -> 7 | I8: https://www.johnsonhealthtech.com/ | J8: https://www.johnsonhealthtech.com/us/eng/careers | K8: https://www.johnsonhealthtech.com/us/eng/careers | L8: https://recruiting.paylocity.com/recruiting/jobs/List/2034/Johnson-Heath-Tech-Companies | M8: Check the Cottage Grove postings and send a concise note about hardware / embedded interest. | N8: Not contacted | P8: =IF(O8<>"",O8+7,"")
A9: Promega | B9: Madison | C9: Scientific instruments / benchtop systems | D9: Madison-headquartered manufacturer that develops reagents and instruments, with engineering and instrument-service roles. | E9: Useful if you want to enter hardware through scientific instruments, system integration, service, or manufacturing engineering. | F9: 3 | G9: 4 | H9: =SUM(F9:G9) -> 7 | I9: https://www.promega.com/ | J9: https://www.promega.com/aboutus/careers/ | K9: https://www.promega.com/aboutus/company-information/ | L9: https://www.promega.com/aboutus/press-releases/global/2022/may-17-2022-forensic-laboratories-flexibility-with-spectrum-ce/ | M9: Look for instrument, service, hardware, or manufacturing-engineering roles on the Madison campus. | N9: Not contacted | P9: =IF(O9<>"",O9+7,"")
A10: Springs Window Fashions | B10: Middleton | C10: Connected products / firmware / controls | D10: Middleton team is hiring firmware and electrical engineers for motorized and connected products, plus internships. | E10: Not semiconductor, but a very real nearby embedded-products employer. | F10: 3 | G10: 4 | H10: =SUM(F10:G10) -> 7 | I10: https://springswindowfashions.com/ | J10: https://springswindowfashions.com/careers/career-opportunities/ | K10: https://springswindowfashions.com/careers/career-opportunities/ | L10: https://careers-springswindowfashions.icims.com/jobs/12354/firmware-engineer/job | M10: Track firmware/electrical roles and mention interest in controls, connected devices, and embedded systems. | N10: Not contacted | P10: =IF(O10<>"",O10+7,"")
A11: Qolab | B11: Madison | C11: Quantum hardware / semiconductor-compatible fabrication | D11: Madison lab building superconducting quantum hardware with advanced semiconductor-compatible fabrication. | E11: Good advanced-hardware startup target for conversations about control, packaging, readout, and scalable hardware systems. | F11: 4 | G11: 3 | H11: =SUM(F11:G11) -> 7 | I11: https://qolab.ai/ | J11: https://qolab.ai/contact-us/ | K11: https://qolab.ai/ | L11: https://qolab.ai/contact-us/ | M11: Send a concise hardware-interest note and watch for lab or hardware-engineering openings. | N11: Not contacted | P11: =IF(O11<>"",O11+7,"")
A12: CAMECA Instruments (Atom Probe Technology Center) | B12: Fitchburg / Madison | C12: Semiconductor metrology / instrumentation | D12: Madison-area site develops and manufactures LEAP atom probe tools used in materials and semiconductor work. | E12: Relevant if you can enter through electronics, test, instrumentation, or manufacturing-engineering-adjacent work. | F12: 3 | G12: 3 | H12: =SUM(F12:G12) -> 6 | I12: https://www.cameca.com/ | J12: https://www.cameca.com/company/careers | K12: https://www.cameca.com/contact/production-sites/atom-probe-technology-center | L12: https://www.cameca.com/company/careers | M12: Check Madison-site openings and look for electronics, instrument, test, or manufacturing roles. | N12: Not contacted | P12: =IF(O12<>"",O12+7,"")
A13: Infleqtion | B13: Madison | C13: Quantum hardware / sensing | D13: Quantum technology company with a Madison office spanning hardware, sensing, and software. | E13: Less direct than X-ES, but still worth tracking for hardware / experimental systems opportunities. | F13: 3 | G13: 3 | H13: =SUM(F13:G13) -> 6 | I13: https://infleqtion.com/ | J13: https://infleqtion.com/careers/ | K13: https://infleqtion.com/careers/ | L13: https://infleqtion.com/infleqtion-and-university-of-colorado-boulder-collaborate/ | M13: Track openings and send a short Madison-office note if you see a hardware-adjacent fit. | N13: Not contacted | P13: =IF(O13<>"",O13+7,"")
A14: Thermo Fisher Scientific | B14: Madison | C14: Analytical instrumentation / service / software | D14: Madison remains a real Thermo Fisher instrument site, with local service/support and instrument/software activity. | E14: Not your purest digital-design fit, but worth watching for hardware-support, instrumentation, automation, or local software roles. | F14: 3 | G14: 3 | H14: =SUM(F14:G14) -> 6 | I14: https://www.thermofisher.com/us/en/home.html | J14: https://jobs.thermofisher.com/ | K14: https://www.thermofisher.com/us/en/home/technical-resources/manufacturing-site-iso-certifications.html | L14: https://jobs.thermofisher.com/global/en/job/R-01346167/Software-Development-Manager | M14: Search Madison openings with keywords like instrument, hardware, automation, validation, software, and service. | N14: Not contacted | P14: =IF(O14<>"",O14+7,"")
... A18: Type One Energy | B18: Madison | C18: Fusion hardware / controls / advanced energy | D18: Madison office in a venture-backed fusion company with local presence and technical roles. | E18: Longer-shot for digital design, but still worth keeping on the board for serious hard-tech networking. | F18: 3 | G18: 2 | H18: =SUM(F18:G18) -> 5 | I18: https://typeoneenergy.com/home/ | J18: https://typeoneenergy.com/careers/ | K18: https://typeoneenergy.com/careers/ | L18: https://typeoneenergy.teamtailor.com/jobs | M18: Track Madison openings and keep this as a network target rather than a primary first outreach wave. | N18: Not contacted | P18: =IF(O18<>"",O18+7,"")

Sheet Resources
A1: Places to mine more local leads
A2: Resource | B2: Why it matters | C2: URL
A3: Wisconsin CHIPS | B3: Statewide semiconductor hub; useful for finding ecosystem players, labs, and events. | C3: https://chips.wisc.edu/
A4: WEDC Innovation Investment Portfolio | B4: Good place to scan Wisconsin startup names and funding-stage signals. | C4: https://wedc.org/innovate-in-wisconsin/innovation-investment-portfolio/
A5: WARF Ventures | B5: UW-Madison commercialization ecosystem; useful for spinout discovery. | C5: https://www.warf.org/warf-ventures/
A6: UW semiconductors news / facilities | B6: Shows what centers, faculty, and spinouts are active around Madison. | C6: https://engineering.wisc.edu/news/new-facility-establishes-uw-madison-as-a-hub-for-next-generation-semiconductors/
A7: SEMICON ecosystem map | B7: National semiconductor ecosystem map if you decide to expand beyond Madison. | C7: https://www.semiconductors.org/ecosystem/

Sheet Outreach_Template
A1: Cold outreach template — customize before sending
A3: Subject line options | B3: UW–Madison digital design student interested in [Company] Quick question from a UW–Madison FPGA / RTL student Aspiring digital design engineer interested in your hardware team
A9: 5-sentence email / LinkedIn note | B9: Hi [Name], I’m a UW–Madison computer engineering student focused on digital design, RTL, FPGA, and hardware systems. I’ve been building experience through coursework and projects in SystemVerilog / Verilog, embedded systems, and verification, and I’m reaching out because I’m very interested in the kind of hardware work [Company] does. What especially caught my eye was [specific company detail]. I’d love to ask a few questions about how someone early in their career could break into this kind of work, and whether there are any student, co-op, test, validation, or junior hardware paths I should keep an eye on. Thank you, [Your Name]
A15: Customization checklist | B15: 1) Mention one company-specific detail. 2) Mention one real project or class. 3) Keep it under ~170 words. 4) Ask for advice or a short conversation, not a job demand.

Sheet Tracker_Blank
A1: Outreach tracker
A2: Company | B2: Contact / role | C2: Where found | D2: Date sent | E2: Follow-up due | F2: Response | G2: Next step | H2: Notes
A3: =Companies!A3 -> Extreme Engineering Solutions (X-ES) | B3: broad | E3: =IF(D3<>"",D3+7,"") | F3: No reply yet | H3: sent a drop box message on 06/01/26, will call in the future.
A4: =Companies!A4 -> i3 Product Development | B4: broad | E4: =IF(D4<>"",D4+7,"") | F4: No reply yet | H4: sent a broad application on 06/01/26, purely explorative
A5: =Companies!A5 -> SixLine Semiconductor | B5: broad | E5: =IF(D5<>"",D5+7,"") | F5: No reply yet | H5: sent a google form in on 06/01/26, explorative.
A6: =Companies!A6 -> Sound Devices | E6: =IF(D6<>"",D6+7,"") | F6: No reply yet
A7: =Companies!A7 -> Sub-Zero Group | E7: =IF(D7<>"",D7+7,"") | F7: No reply yet
A8: =Companies!A8 -> Johnson Health Tech | E8: =IF(D8<>"",D8+7,"") | F8: No reply yet
A9: =Companies!A9 -> Promega | E9: =IF(D9<>"",D9+7,"") | F9: No reply yet
A10: =Companies!A10 -> Springs Window Fashions | E10: =IF(D10<>"",D10+7,"") | F10: No reply yet
A11: =Companies!A11 -> Qolab | E11: =IF(D11<>"",D11+7,"") | F11: No reply yet
A12: =Companies!A12 -> CAMECA Instruments (Atom Probe Technology Center) | E12: =IF(D12<>"",D12+7,"") | F12: No reply yet
A13: =Companies!A13 -> Infleqtion | E13: =IF(D13<>"",D13+7,"") | F13: No reply yet
A14: =Companies!A14 -> Thermo Fisher Scientific | E14: =IF(D14<>"",D14+7,"") | F14: No reply yet
A15: =Companies!A15 -> SHINE Technologies | E15: =IF(D15<>"",D15+7,"") | F15: No reply yet
A16: =Companies!A16 -> NorthStar Medical Radioisotopes | E16: =IF(D16<>"",D16+7,"") | F16: No reply yet
A17: =Companies!A17 -> ABS Global / Genus | E17: =IF(D17<>"",D17+7,"") | F17: No reply yet
A18: =Companies!A18 -> Type One Energy | E18: =IF(D18<>"",D18+7,"") | F18: No reply yet
A19: Milwaukee Tool
